odoo/addons/mrp_bom_find_ignore/README.rst
odoo/addons/mrp_bom_find_ignore/__init__.py
odoo/addons/mrp_bom_find_ignore/__manifest__.py
odoo/addons/mrp_bom_find_ignore/i18n/it.po
odoo/addons/mrp_bom_find_ignore/i18n/mrp_bom_find_ignore.pot
odoo/addons/mrp_bom_find_ignore/models/__init__.py
odoo/addons/mrp_bom_find_ignore/models/mrp_bom.py
odoo/addons/mrp_bom_find_ignore/readme/CONTRIBUTORS.rst
odoo/addons/mrp_bom_find_ignore/readme/DESCRIPTION.rst
odoo/addons/mrp_bom_find_ignore/static/description/icon.png
odoo/addons/mrp_bom_find_ignore/static/description/index.html
odoo/addons/mrp_bom_find_ignore/tests/__init__.py
odoo/addons/mrp_bom_find_ignore/tests/test_mrp_bom_find.py
odoo14_addon_mrp_bom_find_ignore-14.0.1.0.1.dev4.dist-info/METADATA
odoo14_addon_mrp_bom_find_ignore-14.0.1.0.1.dev4.dist-info/WHEEL
odoo14_addon_mrp_bom_find_ignore-14.0.1.0.1.dev4.dist-info/top_level.txt
odoo14_addon_mrp_bom_find_ignore-14.0.1.0.1.dev4.dist-info/RECORD
