Metadata-Version: 2.1
Name: odoo14-addon-mrp_bom_find_ignore
Version: 14.0.1.0.1.dev4
Summary: Adding 'ignore_bom_find' to the context will let '_bom_find' return an empty record set
Home-page: https://github.com/OCA/manufacture
Author: MT Software, Odoo Community Association (OCA)
Author-email: support@odoo-community.org
License: LGPL-3
Classifier: Programming Language :: Python
Classifier: Framework :: Odoo
Classifier: Framework :: Odoo :: 14.0
Classifier: License :: OSI Approved :: GNU Lesser General Public License v3 (LGPLv3)
Requires-Python: >=3.6
Requires-Dist: odoo<14.1dev,>=14.0a
